{"items":{"serializeList":[{"name":"hay","nr":23211047.0},{"name":"wood","nr":101306236.0},{"name":"carrot","nr":3884385.0},{"name":"pumpkin","nr":54548.0},{"name":"cactus","nr":55227.0},{"name":"bone","nr":22155.0},{"name":"weird_substance","nr":191391.0},{"name":"gold","nr":76.0},{"name":"water","nr":238254.0},{"name":"fertilizer","nr":21149.0},{"name":"power","nr":4946.103500000048}]},"dockedFiles":[],"minimizedFiles":["cactus","dinosaur","maze","polyculture","util","weird_susbstance"],"openFilePositions":[{"key":"cactus","value":{"x":472.7349853515625,"y":-706.8739013671875}},{"key":"carrot","value":{"x":1334.17822265625,"y":-1093.7420654296875}},{"key":"dinosaur","value":{"x":467.32159423828127,"y":-1193.2308349609375}},{"key":"hay","value":{"x":-267.640625,"y":-825.703857421875}},{"key":"main","value":{"x":-1099.546875,"y":1009.8492431640625}},{"key":"maze","value":{"x":474.05682373046877,"y":-765.7801513671875}},{"key":"movement","value":{"x":1197.3271484375,"y":-393.1090087890625}},{"key":"polyculture","value":{"x":473.177490234375,"y":-652.0638427734375}},{"key":"pumpkin","value":{"x":1391.3021240234375,"y":222.54034423828126}},{"key":"util","value":{"x":471.24609375,"y":-1141.7642822265625}},{"key":"weird_susbstance","value":{"x":458.863037109375,"y":-993.6927490234375}},{"key":"wood","value":{"x":467.9794921875,"y":-872.1392822265625}},{"key":"docs2","value":{"x":-1098.624755859375,"y":258.24139404296877}},{"key":"sunflower","value":{"x":1393.643798828125,"y":847.67529296875}}],"openFileScrollPositions":[{"key":"cactus","value":0.0},{"key":"carrot","value":763.2988891601563},{"key":"dinosaur","value":-0.00048828125},{"key":"hay","value":-0.0006103515625},{"key":"main","value":-0.00079345703125},{"key":"maze","value":0.0},{"key":"movement","value":199.99859619140626},{"key":"polyculture","value":0.0},{"key":"pumpkin","value":-0.0010986328125},{"key":"util","value":0.0},{"key":"weird_susbstance","value":0.0},{"key":"wood","value":650.0},{"key":"sunflower","value":0.0}],"openFileSizes":[{"key":"cactus","value":{"x":0.0,"y":0.0}},{"key":"carrot","value":{"x":0.0,"y":0.0}},{"key":"dinosaur","value":{"x":0.0,"y":0.0}},{"key":"hay","value":{"x":0.0,"y":0.0}},{"key":"main","value":{"x":1124.3900146484375,"y":762.6153564453125}},{"key":"maze","value":{"x":0.0,"y":0.0}},{"key":"movement","value":{"x":0.0,"y":0.0}},{"key":"polyculture","value":{"x":0.0,"y":0.0}},{"key":"pumpkin","value":{"x":0.0,"y":0.0}},{"key":"util","value":{"x":0.0,"y":0.0}},{"key":"weird_susbstance","value":{"x":0.0,"y":0.0}},{"key":"wood","value":{"x":0.0,"y":0.0}},{"key":"docs2","value":{"x":1135.5723876953125,"y":1659.3641357421875}},{"key":"sunflower","value":{"x":0.0,"y":0.0}}],"openDocPages":[{"key":"docs2","value":"docs/output.md"}],"unlocks":["grass_10","soil","harvest","pass","do_a_flip","pet_the_piggy","grassland","hay","straw_hat","while","true","false","break","continue","loops","speed_5","can_harvest","if","else","elif","expand_7","move","north","south","east","west","for","range","get_world_size","wood","bush","entities","clear","plant","traffic_cone","carrots_10","carrot","till","can_trade","trade","items","carrot_seed","print","quick_print","unlocks","str","debug","and","or","not","operators","variables","watering_9","water","use_item","get_water","functions","def","return","global","get_entity_type","get_ground_type","grounds","get_pos_x","get_pos_y","none","num_items","num_unlocked","senses","trees_10","tree","tree_hat","from","import","carrot_hat","pumpkins_8","pumpkin","pumpkin_seed","dead_pumpkin","change_hat","gray_hat","purple_hat","green_hat","brown_hat","hats","append","remove","pop","insert","len","list","lists","weird_substance","fertilizer_4","sunflower_seed","sunflower","power","get_active_power","measure","sunflowers","pumpkin_hat","min","max","abs","random","utilities","get_time","get_tick_count","timing","get_companion","polyculture_3","dicts","sets","add","dict","set","dictionaries","swap","cactus_seed","cactus_2","cactus_hat","traffic_cone_stack","dinosaurs_2","dinosaur","egg","bone","dinosaur_hat","apple","can_move","get_cost","costs","hedge","treasure","gold","mazes_2","set_execution_speed","set_world_size","debug_2","sunflower_hat","auto_unlock","unlock"],"version":3}